cxxheaderparser/__init__.py
cxxheaderparser/__main__.py
cxxheaderparser/dump.py
cxxheaderparser/errors.py
cxxheaderparser/gentest.py
cxxheaderparser/lexer.py
cxxheaderparser/options.py
cxxheaderparser/parser.py
cxxheaderparser/parserstate.py
cxxheaderparser/preprocessor.py
cxxheaderparser/py.typed
cxxheaderparser/simple.py
cxxheaderparser/tokfmt.py
cxxheaderparser/types.py
cxxheaderparser/version.py
cxxheaderparser/visitor.py
cxxheaderparser/_ply/__init__.py
cxxheaderparser/_ply/lex.py
cxxheaderparser-1.5.4.dist-info/licenses/LICENSE.txt
cxxheaderparser-1.5.4.dist-info/METADATA
cxxheaderparser-1.5.4.dist-info/WHEEL
cxxheaderparser-1.5.4.dist-info/top_level.txt
cxxheaderparser-1.5.4.dist-info/RECORD
