Metadata-Version: 2.4
Name: cxxheaderparser
Version: 1.5.4
Summary: Parse C++ header files and generate a data structure representing the class
Home-page: https://github.com/robotpy/cxxheaderparser
Author: Dustin Spicuzza
Author-email: dustin@virtualroadside.com
Maintainer: RobotPy Development Team
Maintainer-email: robotpy@googlegroups.com
License: BSD
Keywords: c++ header parser ply
Platform: Platform Independent
Classifier: Development Status :: 4 - Beta
Classifier: Operating System :: OS Independent
Classifier: Programming Language :: Python
Classifier: Programming Language :: Python :: 3
Classifier: Programming Language :: C++
Classifier: License :: OSI Approved :: BSD License
Classifier: Intended Audience :: Developers
Classifier: Topic :: Software Development
Classifier: Topic :: Software Development :: Code Generators
Classifier: Topic :: Software Development :: Compilers
Requires-Python: >= 3.6
License-File: LICENSE.txt
Requires-Dist: dataclasses; python_version < "3.7"
Provides-Extra: pcpp
Requires-Dist: pcpp~=1.30; extra == "pcpp"
Dynamic: author
Dynamic: author-email
Dynamic: classifier
Dynamic: description
Dynamic: description-content-type
Dynamic: home-page
Dynamic: keywords
Dynamic: license
Dynamic: license-file
Dynamic: maintainer
Dynamic: maintainer-email
Dynamic: platform
Dynamic: provides-extra
Dynamic: requires-dist
Dynamic: requires-python
Dynamic: summary
